FamzzXMadBypass/FamzzXMadBypass.py
FamzzXMadBypass/__init__.py
FamzzXMadBypass-0.1.3.dist-info/METADATA
FamzzXMadBypass-0.1.3.dist-info/WHEEL
FamzzXMadBypass-0.1.3.dist-info/top_level.txt
FamzzXMadBypass-0.1.3.dist-info/RECORD
