Metadata-Version: 2.1
Name: FamzzXMadBypass
Version: 0.1.3
Summary: A module to bypass Adlink
Author: Famzz X Mad
Classifier: Programming Language :: Python :: 3
Classifier: License :: OSI Approved :: MIT License
Classifier: Operating System :: OS Independent
Requires-Python: >=3.6
Requires-Dist: requests
